BioMatcher/Algorithms_old.py
BioMatcher/Cleaner.py
BioMatcher/Cleaner_tests.py
BioMatcher/Exceptions.py
BioMatcher/Filter.py
BioMatcher/Filter_tests.py
BioMatcher/GUI.py
BioMatcher/Manager.py
BioMatcher/Matcher.py
BioMatcher/Matcher_tests.py
BioMatcher/Output.py
BioMatcher/Tests_old.py
BioMatcher/UserInterface.py
BioMatcher/__init__.py
BioMatcher/setup.py
BioMatcher-1.0.dist-info/LICENSE
BioMatcher-1.0.dist-info/METADATA
BioMatcher-1.0.dist-info/WHEEL
BioMatcher-1.0.dist-info/top_level.txt
BioMatcher-1.0.dist-info/RECORD
