Metadata-Version: 2.1
Name: BioMatcher
Version: 1.0
Summary: BioMatcher helps you find microRNAs with the same seed
Home-page: https://github.com/cmencar/bio-01
Author: Antonio Donvito
Author-email: a.donvito20@studenti.uniba.it
License: UNKNOWN
Platform: UNKNOWN
Classifier: Programming Language :: Python :: 3
Classifier: License :: OSI Approved :: MIT License
Classifier: Operating System :: OS Independent
